redis_observer/__init__.py
redis_observer/logstream.py
redis_observer-0.0.1.dist-info/LICENSE
redis_observer-0.0.1.dist-info/METADATA
redis_observer-0.0.1.dist-info/WHEEL
redis_observer-0.0.1.dist-info/top_level.txt
redis_observer-0.0.1.dist-info/RECORD
