Metadata-Version: 2.1
Name: redis-observer
Version: 0.0.1
Summary: Track Usage, Log events from any python script into redis streams
Home-page: https://github.com/Redislabs-Solution-Architects/redis-observer
Author: Omkar Konnur
Author-email: omkar.konnur@redis.com
License: MIT
Project-URL: Bug Tracker, https://github.com/Redislabs-Solution-Architects/redis-observer/issues
License-File: LICENSE
Requires-Dist: redis
